discord_webhook/__init__.py
discord_webhook/__main__.py
discord_webhook/async_webhook.py
discord_webhook/py.typed
discord_webhook/webhook.py
discord_webhook/webhook_exceptions.py
py_discord_hook-1.3.2.dist-info/entry_points.txt
py_discord_hook-1.3.2.dist-info/LICENSE
py_discord_hook-1.3.2.dist-info/WHEEL
py_discord_hook-1.3.2.dist-info/METADATA
py_discord_hook-1.3.2.dist-info/RECORD
