Metadata-Version: 2.1
Name: py-discord-hook
Version: 1.3.2
Summary: Easily send Discord webhooks with Python
Home-page: https://github.com/rawandahmad698/discord-hook
License: MIT
Keywords: discord,webhook
Author: lovvskillz
Author-email: 14542790+lovvskillz@users.noreply.github.com
Requires-Python: >=3.10,<4.0
Classifier: License :: OSI Approved :: MIT License
Classifier: Programming Language :: Python :: 3
Classifier: Programming Language :: Python :: 3.10
Provides-Extra: async
Requires-Dist: httpx (>=0.23.2,<0.24.0); extra == "async"
Requires-Dist: requests (>=2.28.1,<3.0.0)
Project-URL: Repository, https://github.com/rawandahmad698/discord-hook
